shr_span_recorder/__init__.py
shr_span_recorder/_werkzeug.py
shr_span_recorder/_wsgi_common.py
shr_span_recorder/consts.py
shr_span_recorder/integration.py
shr_span_recorder/wsgi.py
shr_span_recorder-0.1.0.dist-info/licenses/AUTHORS.rst
shr_span_recorder-0.1.0.dist-info/licenses/LICENSE
shr_span_recorder-0.1.0.dist-info/METADATA
shr_span_recorder-0.1.0.dist-info/WHEEL
shr_span_recorder-0.1.0.dist-info/top_level.txt
shr_span_recorder-0.1.0.dist-info/RECORD
