Metadata-Version: 2.4
Name: shr_span_recorder
Version: 0.1.0
Summary: Record spans in Sentry even if they occur while the response is being streamed
Author-email: Nick ODell <nickodell@gmail.com>
Maintainer-email: Nick ODell <nickodell@gmail.com>
License-Expression: MIT
Project-URL: bugs, https://github.com/nickodell/shr_span_recorder/issues
Project-URL: changelog, https://github.com/nickodell/shr_span_recorder/blob/master/changelog.md
Project-URL: homepage, https://github.com/nickodell/shr_span_recorder
License-File: LICENSE
License-File: AUTHORS.rst
Requires-Dist: sentry-sdk>=2.12.0
Provides-Extra: dev
Requires-Dist: coverage; extra == "dev"
Requires-Dist: mypy; extra == "dev"
Requires-Dist: pytest; extra == "dev"
Requires-Dist: ruff; extra == "dev"
Dynamic: license-file
